checkmaster/__init__.py
checkmaster/checkmaster.py
checkmaster/commands.py
checkmaster/distribution.py
checkmaster/filesystems.py
checkmaster/hardware.py
checkmaster/sockets.py
checkmaster/status.py
checkmaster/users_groups.py
checkmaster/bin/checkmaster
checkmaster-0.9.7.data/scripts/checkmaster
checkmaster-0.9.7.dist-info/LICENSE
checkmaster-0.9.7.dist-info/METADATA
checkmaster-0.9.7.dist-info/WHEEL
checkmaster-0.9.7.dist-info/top_level.txt
checkmaster-0.9.7.dist-info/RECORD
