Metadata-Version: 2.1
Name: checkmaster
Version: 0.9.7
Summary: Tool that checks the system capabilities
Home-page: https://github.com/peppelinux/checkmaster
Author: Giuseppe De Marco
Author-email: demarcog83@gmail.com
License: License :: OSI Approved :: GNU Affero General Public License v3
Classifier: Development Status :: 5 - Production/Stable
Classifier: License :: OSI Approved :: GNU Affero General Public License v3
Classifier: Programming Language :: Python :: 3
License-File: LICENSE
Requires-Dist: pyYaml
Requires-Dist: psutil
Requires-Dist: distro
Requires-Dist: coloredlogs
Requires-Dist: netifaces
Requires-Dist: requests
